<ipojo xmlns:xsi="http://www.w3.org/2001/XMLSchema-instance"
	xsi:schemaLocation="org.apache.felix.ipojo http://felix.apache.org/ipojo/schemas/CURRENT/core.xsd"
	xmlns="org.apache.felix.ipojo">
	<instance component="logger-registry" />
	<instance component="logger-factory-registry" />
	<instance component="logapi-script-factory" />
	<instance component="log-parser-registry" />
	<instance component="log-parser-factory-registry" />
	<instance component="log-normalizer-registry" />
	<instance component="text-file-logger-factory" />
	<instance component="logapi-logger-plugin" />
	<instance component="delimiter-parser-factory" />
</ipojo>